{"trial_id": "2", "hyperparameters": {"space": [{"class_name": "Int", "config": {"name": "num_layers", "default": null, "conditions": [], "min_value": 2, "max_value": 5, "step": 1, "sampling": null}}, {"class_name": "Int", "config": {"name": "units_0", "default": null, "conditions": [], "min_value": 8, "max_value": 256, "step": 32, "sampling": null}}, {"class_name": "Int", "config": {"name": "units_1", "default": null, "conditions": [], "min_value": 8, "max_value": 256, "step": 32, "sampling": null}}, {"class_name": "Choice", "config": {"name": "learning_rate", "default": 0.01, "conditions": [], "values": [0.01, 0.001, 0.0001], "ordered": true}}, {"class_name": "Int", "config": {"name": "units_2", "default": null, "conditions": [], "min_value": 8, "max_value": 256, "step": 32, "sampling": null}}, {"class_name": "Int", "config": {"name": "units_3", "default": null, "conditions": [], "min_value": 8, "max_value": 256, "step": 32, "sampling": null}}, {"class_name": "Int", "config": {"name": "units_4", "default": null, "conditions": [], "min_value": 8, "max_value": 256, "step": 32, "sampling": null}}], "values": {"num_layers": 5, "units_0": 40, "units_1": 8, "learning_rate": 0.01, "units_2": 40, "units_3": 40, "units_4": 8}}, "metrics": {"metrics": {"loss": {"direction": "min", "observations": [{"value": [22.902060826619465], "step": 2}]}, "accuracy": {"direction": "max", "observations": [{"value": [0.5978287061055502], "step": 2}]}, "val_loss": {"direction": "min", "observations": [{"value": [21.445437749226887], "step": 2}]}, "val_accuracy": {"direction": "max", "observations": [{"value": [0.6994693676630656], "step": 2}]}}}, "score": 0.6994693676630656, "best_step": 2, "status": "COMPLETED"}